{
  "query": "news",
  "archivedAt": "2026-04-11T08:09:17.117Z",
  "merkleRoot": "0x7245f90d650e38dc3ae76d4d9adef476ad21f1a77e65b13cf2c6457c76269010",
  "results": [
    {
      "url": "https://abcnews.com/US/people-injured-after-struck-car-louisiana-parade-driver/story?id=131733072",
      "title": "Man charged with impaired driving after car plows into ...",
      "snippet": "6 days ago · Man charged with impaired driving after car plows into pedestrians during Louisiana parade: Authorities Several people were hurt, including some seriously, authorities said.",
      "pageHTML": "",
      "contentHash": "7245f90d650e38dc3ae76d4d9adef476ad21f1a77e65b13cf2c6457c76269010",
      "fetchedAt": "2026-04-11T08:09:17.116Z"
    }
  ]
}